[
  {
    "id": "2b3f687e",
    "ts": "2026-06-14T15:02:16.950993",
    "level": "WARN",
    "site": "company_careers",
    "message": "Failed to apply at https://jobs.lever.co/valarian/872aec4d-d770-4962-a374-b278d…: Page.goto: Target page, context or browser has been closed"
  },
  {
    "id": "bf1369de",
    "ts": "2026-06-14T15:02:16.975072",
    "level": "INFO",
    "site": "company_careers",
    "message": "Processing: https://jobs.lever.co/playonsports/78469e7c-24d5-4a02-912e-6ec65f156178#:~:text=…"
  },
  {
    "id": "4d9d0ebd",
    "ts": "2026-06-14T15:02:17.011535",
    "level": "WARN",
    "site": "company_careers",
    "message": "Failed to apply at https://jobs.lever.co/playonsports/78469e7c-24d5-4a02-912e-6…: Page.goto: Target page, context or browser has been closed"
  },
  {
    "id": "965a2a54",
    "ts": "2026-06-14T15:02:17.044174",
    "level": "INFO",
    "site": "company_careers",
    "message": "✅ Company Careers bot finished. Applied to 0 positions."
  },
  {
    "id": "e44a67c6",
    "ts": "2026-06-14T15:02:17.096915",
    "level": "INFO",
    "site": "system",
    "message": "--- Company Careers done ---"
  },
  {
    "id": "3d61f14a",
    "ts": "2026-06-14T15:02:17.383453",
    "level": "INFO",
    "site": "system",
    "message": "--- Company Careers done ---"
  }
]